{"title":"네이버 뉴스 ─ 분야별 주요뉴스","url":"https://news.naver.com/main/main.naver?mode=LSD&mid=shm&sid1=100","favicon":"https://news.naver.com/main/favicon.ico","elements":[{"title":"신원식 국방장관 후보자 청문보고서 채택 사실상 무산","contents":"<a href=\"https://n.news.naver.com/mnews/article/056/0011576156?sid=100\" class=\"nclicks(rig.secteco)\" title=\"신원식 국방장관 후보자 청문보고서 채택 사실상 무산\">신원식 국방장관 후보자 청문보고서 채택 사실상 무산</a>","link":"https://n.news.naver.com/mnews/article/056/0011576156?sid=100","retrieved":1696475575883},{"title":"박지원 “진교훈, 10%p이상 차이로 이긴다. 김기현 아웃->비대위 온다”[시선집중]","contents":"<a href=\"https://n.news.naver.com/mnews/article/214/0001303456?sid=100\" class=\"nclicks(rig.secteco)\" title=\" 박지원 “진교훈, 10%p이상 차이로 이긴다. 김기현 아웃->비대위 온다”[시선집중]\"> 박지원 “진교훈, 10%p이상 차이로 이긴다. 김기현 아웃-&gt;비대위 온다”[시선집중]</a>","link":"https://n.news.naver.com/mnews/article/214/0001303456?sid=100","retrieved":1696475575884},{"title":"한일 외교차관 전략대화 개최…전략적 공조 방안 모색","contents":"<a href=\"https://n.news.naver.com/mnews/article/003/0012128348?sid=100\" class=\"nclicks(rig.secteco)\" title=\"한일 외교차관 전략대화 개최…전략적 공조 방안 모색\">한일 외교차관 전략대화 개최…전략적 공조 방안 모색</a>","link":"https://n.news.naver.com/mnews/article/003/0012128348?sid=100","retrieved":1696475575884},{"title":"후쿠시마 오염수, 또 방류…\"삼중수소 기준치보다 낮아\"","contents":"<a href=\"https://n.news.naver.com/mnews/article/277/0005322162?sid=104\" class=\"nclicks(rig.secteco)\" title=\"후쿠시마 오염수, 또 방류…&quot;삼중수소 기준치보다 낮아&quot;\">후쿠시마 오염수, 또 방류…\"삼중수소 기준치보다 낮아\"</a>","link":"https://n.news.naver.com/mnews/article/277/0005322162?sid=104","retrieved":1696475575884},{"title":"영 수낵 총리 \"북부 고속철도 사업 폐기…'비흡연 세대' 만든다\"","contents":"<a href=\"https://n.news.naver.com/mnews/article/055/0001094716?sid=104\" class=\"nclicks(rig.secteco)\" title=\"영 수낵 총리 &quot;북부 고속철도 사업 폐기…'비흡연 세대' 만든다&quot;\">영 수낵 총리 \"북부 고속철도 사업 폐기…'비흡연 세대' 만든다\"</a>","link":"https://n.news.naver.com/mnews/article/055/0001094716?sid=104","retrieved":1696475575887},{"title":"해수부, 디지털 해상교통 정보사업 육성…세계적 기업 키운다","contents":"<a href=\"https://n.news.naver.com/mnews/article/003/0012127731?sid=101\" class=\"nclicks(rig.secteco)\" title=\"해수부, 디지털 해상교통 정보사업 육성…세계적 기업 키운다\">해수부, 디지털 해상교통 정보사업 육성…세계적 기업 키운다</a>","link":"https://n.news.naver.com/mnews/article/003/0012127731?sid=101","retrieved":1696475575891},{"title":"지금도 '소맥' 1만원 넘는데…맥주 가격 인상에 '촉각'","contents":"<a href=\"https://n.news.naver.com/mnews/article/586/0000065307?sid=101\" class=\"nclicks(rig.secteco)\" title=\"지금도 '소맥' 1만원 넘는데…맥주 가격 인상에 '촉각'\">지금도 '소맥' 1만원 넘는데…맥주 가격 인상에 '촉각'</a>","link":"https://n.news.naver.com/mnews/article/586/0000065307?sid=101","retrieved":1696475575893},{"title":"관세청 \"마약 청정국 지위 회복…비관세장벽 해소\"","contents":"<a href=\"https://n.news.naver.com/mnews/article/001/0014239541?sid=101\" class=\"nclicks(rig.secteco)\" title=\"관세청 &quot;마약 청정국 지위 회복…비관세장벽 해소&quot;\">관세청 \"마약 청정국 지위 회복…비관세장벽 해소\"</a>","link":"https://n.news.naver.com/mnews/article/001/0014239541?sid=101","retrieved":1696475575905},{"title":"삼성 갤럭시워치로 '수면 무호흡' 발견…식약처 허가","contents":"<a href=\"https://n.news.naver.com/mnews/article/374/0000353356?sid=101\" class=\"nclicks(rig.secteco)\" title=\"삼성 갤럭시워치로 '수면 무호흡' 발견…식약처 허가\">삼성 갤럭시워치로 '수면 무호흡' 발견…식약처 허가</a>","link":"https://n.news.naver.com/mnews/article/374/0000353356?sid=101","retrieved":1696475575907},{"title":"제2 카카오 먹통 사태 막는다…방통위, 법령 개정 추진","contents":"<a href=\"https://n.news.naver.com/mnews/article/277/0005322477?sid=105\" class=\"nclicks(rig.secteco)\" title=\"제2 카카오 먹통 사태 막는다…방통위, 법령 개정 추진\">제2 카카오 먹통 사태 막는다…방통위, 법령 개정 추진</a>","link":"https://n.news.naver.com/mnews/article/277/0005322477?sid=105","retrieved":1696475575911},{"title":"광명시 6일부터 '경기정원문화박람회'열어...정원 29개 조성","contents":"<a href=\"https://n.news.naver.com/mnews/article/008/0004945045?sid=102\" class=\"nclicks(rig.secteco)\" title=\"광명시 6일부터 '경기정원문화박람회'열어...정원 29개 조성\">광명시 6일부터 '경기정원문화박람회'열어...정원 29개 조성</a>","link":"https://n.news.naver.com/mnews/article/008/0004945045?sid=102","retrieved":1696475575913},{"title":"\"반려동물 장례도 사람처럼\"…펫시장 뛰어드는 상조업체들","contents":"<a href=\"https://n.news.naver.com/mnews/article/421/0007086705?sid=101\" class=\"nclicks(rig.secteco)\" title=\"&quot;반려동물 장례도 사람처럼&quot;…펫시장 뛰어드는 상조업체들\">\"반려동물 장례도 사람처럼\"…펫시장 뛰어드는 상조업체들</a>","link":"https://n.news.naver.com/mnews/article/421/0007086705?sid=101","retrieved":1696475575916},{"title":"대전지검, ‘통계조작 의혹’ 관련 통계청·국토부 등 압수수색","contents":"<a href=\"https://n.news.naver.com/mnews/article/005/0001642284?sid=102\" class=\"nclicks(rig.secteco)\" title=\"대전지검, ‘통계조작 의혹’ 관련 통계청·국토부 등 압수수색\">대전지검, ‘통계조작 의혹’ 관련 통계청·국토부 등 압수수색</a>","link":"https://n.news.naver.com/mnews/article/005/0001642284?sid=102","retrieved":1696475575918},{"title":"강한 바람에 출근길 체감온도 ‘뚝’…강원도엔 ‘얼음’[내일날씨]","contents":"<a href=\"https://n.news.naver.com/mnews/article/022/0003861327?sid=103\" class=\"nclicks(rig.secteco)\" title=\" 강한 바람에 출근길 체감온도 ‘뚝’…강원도엔 ‘얼음’[내일날씨]\"> 강한 바람에 출근길 체감온도 ‘뚝’…강원도엔 ‘얼음’[내일날씨]</a>","link":"https://n.news.naver.com/mnews/article/022/0003861327?sid=103","retrieved":1696475575920},{"title":"\"스트레스에 취약한 사람, 치매 발병 위험 높다\"","contents":"<a href=\"https://n.news.naver.com/mnews/article/001/0014238829?sid=103\" class=\"nclicks(rig.secteco)\" title=\"&quot;스트레스에 취약한 사람, 치매 발병 위험 높다&quot;\">\"스트레스에 취약한 사람, 치매 발병 위험 높다\"</a>","link":"https://n.news.naver.com/mnews/article/001/0014238829?sid=103","retrieved":1696475575922}]}