{"title":"네이버 뉴스 ─ 분야별 주요뉴스","url":"https://news.naver.com/main/main.naver?mode=LSD&mid=shm&sid1=100","favicon":"https://news.naver.com/main/favicon.ico","elements":[{"title":"하마다 日방위상, 北 미사일발사 예고기간 종료에도 파괴조치명령 연장","contents":"<a href=\"https://n.news.naver.com/mnews/article/003/0011906580?sid=104\" class=\"nclicks(rig.secteco)\" title=\"하마다 日방위상, 北 미사일발사 예고기간 종료에도 파괴조치명령 연장\">하마다 日방위상, 北 미사일발사 예고기간 종료에도 파괴조치명령 연장</a>","link":"https://n.news.naver.com/mnews/article/003/0011906580?sid=104","retrieved":1686507286188},{"title":"김기현 \"이재명, 역대급 외교 참사...中 사대주의 DNA\"","contents":"<a href=\"https://n.news.naver.com/mnews/article/052/0001895672?sid=100\" class=\"nclicks(rig.secteco)\" title=\"김기현 &quot;이재명, 역대급 외교 참사...中 사대주의 DNA&quot;\">김기현 \"이재명, 역대급 외교 참사...中 사대주의 DNA\"</a>","link":"https://n.news.naver.com/mnews/article/052/0001895672?sid=100","retrieved":1686507286190},{"title":"\"무얼 할지 고민\"...조국, 文 만나 '독주' 나눠","contents":"<a href=\"https://n.news.naver.com/mnews/article/018/0005505704?sid=100\" class=\"nclicks(rig.secteco)\" title=\"&quot;무얼 할지 고민&quot;...조국, 文 만나 '독주' 나눠\">\"무얼 할지 고민\"...조국, 文 만나 '독주' 나눠</a>","link":"https://n.news.naver.com/mnews/article/018/0005505704?sid=100","retrieved":1686507286190},{"title":"테슬라, 오토파일럿·FSD 관련 사고 급증…4년간 736건","contents":"<a href=\"https://n.news.naver.com/mnews/article/018/0005505697?sid=101\" class=\"nclicks(rig.secteco)\" title=\"테슬라, 오토파일럿·FSD 관련 사고 급증…4년간 736건\">테슬라, 오토파일럿·FSD 관련 사고 급증…4년간 736건</a>","link":"https://n.news.naver.com/mnews/article/018/0005505697?sid=101","retrieved":1686507286193},{"title":"루마니아, 아프리카인 원숭이에 비유 주케냐 대사 소환","contents":"<a href=\"https://n.news.naver.com/mnews/article/001/0013995056?sid=104\" class=\"nclicks(rig.secteco)\" title=\"루마니아, 아프리카인 원숭이에 비유 주케냐 대사 소환\">루마니아, 아프리카인 원숭이에 비유 주케냐 대사 소환</a>","link":"https://n.news.naver.com/mnews/article/001/0013995056?sid=104","retrieved":1686507286194},{"title":"美증시 강세장 계속될까…CPI 반영한 이번주 연준 금리결정이 관건","contents":"<a href=\"https://n.news.naver.com/mnews/article/018/0005506021?sid=101\" class=\"nclicks(rig.secteco)\" title=\"美증시 강세장 계속될까…CPI 반영한 이번주 연준 금리결정이 관건\">美증시 강세장 계속될까…CPI 반영한 이번주 연준 금리결정이 관건</a>","link":"https://n.news.naver.com/mnews/article/018/0005506021?sid=101","retrieved":1686507286196},{"title":"기재차관 \"우크라에 1.3억불 신규 지원…재건·복구 적극 참여\"","contents":"<a href=\"https://n.news.naver.com/mnews/article/008/0004897751?sid=101\" class=\"nclicks(rig.secteco)\" title=\"기재차관 &quot;우크라에 1.3억불 신규 지원…재건·복구 적극 참여&quot;\">기재차관 \"우크라에 1.3억불 신규 지원…재건·복구 적극 참여\"</a>","link":"https://n.news.naver.com/mnews/article/008/0004897751?sid=101","retrieved":1686507286200},{"title":"2금융권 연체율 ‘비상’…금감원, 긴급 현장점검 착수","contents":"<a href=\"https://n.news.naver.com/mnews/article/028/0002643389?sid=101\" class=\"nclicks(rig.secteco)\" title=\"2금융권 연체율 ‘비상’…금감원, 긴급 현장점검 착수\">2금융권 연체율 ‘비상’…금감원, 긴급 현장점검 착수</a>","link":"https://n.news.naver.com/mnews/article/028/0002643389?sid=101","retrieved":1686507286200},{"title":"SKB, '우리동네광고'로 강원 지역 창업가 마케팅 돕는다","contents":"<a href=\"https://n.news.naver.com/mnews/article/015/0004854521?sid=105\" class=\"nclicks(rig.secteco)\" title=\"SKB, '우리동네광고'로 강원 지역 창업가 마케팅 돕는다\">SKB, '우리동네광고'로 강원 지역 창업가 마케팅 돕는다</a>","link":"https://n.news.naver.com/mnews/article/015/0004854521?sid=105","retrieved":1686507286201},{"title":"'챗GPT' 올트먼 \"AI 리스크 줄이기 위해 미·중 협력해야\"","contents":"<a href=\"https://n.news.naver.com/mnews/article/052/0001895576?sid=104\" class=\"nclicks(rig.secteco)\" title=\"'챗GPT' 올트먼 &quot;AI 리스크 줄이기 위해 미·중 협력해야&quot;\">'챗GPT' 올트먼 \"AI 리스크 줄이기 위해 미·중 협력해야\"</a>","link":"https://n.news.naver.com/mnews/article/052/0001895576?sid=104","retrieved":1686507286202},{"title":"아파트 놀이터 철제 흔들의자 넘어져 초등학생 숨져","contents":"<a href=\"https://n.news.naver.com/mnews/article/052/0001895694?sid=102\" class=\"nclicks(rig.secteco)\" title=\"아파트 놀이터 철제 흔들의자 넘어져 초등학생 숨져\">아파트 놀이터 철제 흔들의자 넘어져 초등학생 숨져</a>","link":"https://n.news.naver.com/mnews/article/052/0001895694?sid=102","retrieved":1686507286204},{"title":"\"주민들은 내가 지킨다\"…부산 돌려차기男 신상 공개한 구의원","contents":"<a href=\"https://n.news.naver.com/mnews/article/015/0004854462?sid=101\" class=\"nclicks(rig.secteco)\" title=\"&quot;주민들은 내가 지킨다&quot;…부산 돌려차기男 신상 공개한 구의원\">\"주민들은 내가 지킨다\"…부산 돌려차기男 신상 공개한 구의원</a>","link":"https://n.news.naver.com/mnews/article/015/0004854462?sid=101","retrieved":1686507286205},{"title":"이태원 상권 회복세 뚜렷....유동인구·카드매출액↑","contents":"<a href=\"https://n.news.naver.com/mnews/article/014/0005025187?sid=102\" class=\"nclicks(rig.secteco)\" title=\"이태원 상권 회복세 뚜렷....유동인구·카드매출액↑\">이태원 상권 회복세 뚜렷....유동인구·카드매출액↑</a>","link":"https://n.news.naver.com/mnews/article/014/0005025187?sid=102","retrieved":1686507286207},{"title":"전동트렁크 빠진 토요타 크라운, 그랜저 잡을수 있나?[차알못시승기]","contents":"<a href=\"https://n.news.naver.com/mnews/article/008/0004897647?sid=101\" class=\"nclicks(rig.secteco)\" title=\"전동트렁크 빠진 토요타 크라운, 그랜저 잡을수 있나?[차알못시승기]\">전동트렁크 빠진 토요타 크라운, 그랜저 잡을수 있나?[차알못시승기]</a>","link":"https://n.news.naver.com/mnews/article/008/0004897647?sid=101","retrieved":1686507286208},{"title":"현대차 기술캠페인 영상, 美 마케팅 시상식서 최고상","contents":"<a href=\"https://n.news.naver.com/mnews/article/277/0005270963?sid=103\" class=\"nclicks(rig.secteco)\" title=\"현대차 기술캠페인 영상, 美 마케팅 시상식서 최고상\">현대차 기술캠페인 영상, 美 마케팅 시상식서 최고상</a>","link":"https://n.news.naver.com/mnews/article/277/0005270963?sid=103","retrieved":1686507286210}]}