{"title":"네이버 뉴스 ─ 분야별 주요뉴스","url":"https://news.naver.com/main/main.naver?mode=LSD&mid=shm&sid1=100","favicon":"https://news.naver.com/main/favicon.ico","elements":[{"title":"韓 총리 “킬러문항, ‘아이들 데리고 장난친다’ 의견에 동의”","contents":"<a href=\"https://n.news.naver.com/mnews/article/022/0003825551?sid=100\" class=\"nclicks(rig.secteco)\" title=\"韓 총리 “킬러문항, ‘아이들 데리고 장난친다’ 의견에 동의”\">韓 총리 “킬러문항, ‘아이들 데리고 장난친다’ 의견에 동의”</a>","link":"https://n.news.naver.com/mnews/article/022/0003825551?sid=100","retrieved":1687374632685},{"title":"“의원 30명 감축·무노동 무임금·불체포특권 포기하자”","contents":"<a href=\"https://n.news.naver.com/mnews/article/005/0001617613?sid=100\" class=\"nclicks(rig.secteco)\" title=\"“의원 30명 감축·무노동 무임금·불체포특권 포기하자”\">“의원 30명 감축·무노동 무임금·불체포특권 포기하자”</a>","link":"https://n.news.naver.com/mnews/article/005/0001617613?sid=100","retrieved":1687374632689},{"title":"국회 본회의, '반의사 불벌죄 폐지' 스토킹 처벌법 처리","contents":"<a href=\"https://n.news.naver.com/mnews/article/277/0005275578?sid=100\" class=\"nclicks(rig.secteco)\" title=\"국회 본회의, '반의사 불벌죄 폐지' 스토킹 처벌법 처리\">국회 본회의, '반의사 불벌죄 폐지' 스토킹 처벌법 처리</a>","link":"https://n.news.naver.com/mnews/article/277/0005275578?sid=100","retrieved":1687374632690},{"title":"中 '최악' 청년실업률…올여름 신규 대졸자 가세하면 더 악화","contents":"<a href=\"https://n.news.naver.com/mnews/article/422/0000604845?sid=104\" class=\"nclicks(rig.secteco)\" title=\"中 '최악' 청년실업률…올여름 신규 대졸자 가세하면 더 악화\">中 '최악' 청년실업률…올여름 신규 대졸자 가세하면 더 악화</a>","link":"https://n.news.naver.com/mnews/article/422/0000604845?sid=104","retrieved":1687374632691},{"title":"“타이태닉 잠수정 ‘쾅쾅’ 소리”…얼마 안남은 골든타임","contents":"<a href=\"https://n.news.naver.com/mnews/article/081/0003370638?sid=104\" class=\"nclicks(rig.secteco)\" title=\"“타이태닉 잠수정 ‘쾅쾅’ 소리”…얼마 안남은 골든타임\">“타이태닉 잠수정 ‘쾅쾅’ 소리”…얼마 안남은 골든타임</a>","link":"https://n.news.naver.com/mnews/article/081/0003370638?sid=104","retrieved":1687374632697},{"title":"힘 실리는 테슬라 슈퍼차저…GM·포드 이어 리비안도 사용키로(종합)","contents":"<a href=\"https://n.news.naver.com/mnews/article/001/0014015692?sid=101\" class=\"nclicks(rig.secteco)\" title=\"힘 실리는 테슬라 슈퍼차저…GM·포드 이어 리비안도 사용키로(종합)\">힘 실리는 테슬라 슈퍼차저…GM·포드 이어 리비안도 사용키로(종합)</a>","link":"https://n.news.naver.com/mnews/article/001/0014015692?sid=101","retrieved":1687374632698},{"title":"한전 적자에도 전기 요금 '동결'...\"해외에선 신기하게 봐\" [Y녹취록]","contents":"<a href=\"https://n.news.naver.com/mnews/article/052/0001899823?sid=101\" class=\"nclicks(rig.secteco)\" title=\"한전 적자에도 전기 요금 '동결'...&quot;해외에선 신기하게 봐&quot; [Y녹취록]\">한전 적자에도 전기 요금 '동결'...\"해외에선 신기하게 봐\" [Y녹취록]</a>","link":"https://n.news.naver.com/mnews/article/052/0001899823?sid=101","retrieved":1687374632699},{"title":"서산시 ‘대산 수소터빈발전 실증 기념식’ 개최","contents":"<a href=\"https://n.news.naver.com/mnews/article/421/0006880512?sid=102\" class=\"nclicks(rig.secteco)\" title=\"서산시 ‘대산 수소터빈발전 실증 기념식’ 개최\">서산시 ‘대산 수소터빈발전 실증 기념식’ 개최</a>","link":"https://n.news.naver.com/mnews/article/421/0006880512?sid=102","retrieved":1687374632699},{"title":"“AI 총력전”...로봇·건강·교육에 접목해 2025년 매출 1조3000억원","contents":"<a href=\"https://n.news.naver.com/mnews/article/009/0005147207?sid=101\" class=\"nclicks(rig.secteco)\" title=\"“AI 총력전”...로봇·건강·교육에 접목해 2025년 매출 1조3000억원\">“AI 총력전”...로봇·건강·교육에 접목해 2025년 매출 1조3000억원</a>","link":"https://n.news.naver.com/mnews/article/009/0005147207?sid=101","retrieved":1687374632700},{"title":"카카오모빌리티·메가존클라우드…윤 대통령과 '기회의 땅' 베트남 간다","contents":"<a href=\"https://n.news.naver.com/mnews/article/421/0006880180?sid=105\" class=\"nclicks(rig.secteco)\" title=\"카카오모빌리티·메가존클라우드…윤 대통령과 '기회의 땅' 베트남 간다\">카카오모빌리티·메가존클라우드…윤 대통령과 '기회의 땅' 베트남 간다</a>","link":"https://n.news.naver.com/mnews/article/421/0006880180?sid=105","retrieved":1687374632701},{"title":"'1,300억 배상' 엘리엇 말고도 ISDS 최소 5건 진행","contents":"<a href=\"https://n.news.naver.com/mnews/article/052/0001899976?sid=102\" class=\"nclicks(rig.secteco)\" title=\"'1,300억 배상' 엘리엇 말고도 ISDS 최소 5건 진행\">'1,300억 배상' 엘리엇 말고도 ISDS 최소 5건 진행</a>","link":"https://n.news.naver.com/mnews/article/052/0001899976?sid=102","retrieved":1687374632701},{"title":"민노총 '분신' 양회동씨 사망 50일 만에 영결식","contents":"<a href=\"https://n.news.naver.com/mnews/article/654/0000043695?sid=102\" class=\"nclicks(rig.secteco)\" title=\"민노총 '분신' 양회동씨 사망 50일 만에 영결식\">민노총 '분신' 양회동씨 사망 50일 만에 영결식</a>","link":"https://n.news.naver.com/mnews/article/654/0000043695?sid=102","retrieved":1687374632702},{"title":"고1 공통과목 석차등급 병기...학원 부조리 2주간 집중신고","contents":"<a href=\"https://n.news.naver.com/mnews/article/052/0001899866?sid=102\" class=\"nclicks(rig.secteco)\" title=\"고1 공통과목 석차등급 병기...학원 부조리 2주간 집중신고\">고1 공통과목 석차등급 병기...학원 부조리 2주간 집중신고</a>","link":"https://n.news.naver.com/mnews/article/052/0001899866?sid=102","retrieved":1687374632703},{"title":"“올 여름 비키니 입을래” 무리한 다이어트 ‘이 병’ 부른다","contents":"<a href=\"https://n.news.naver.com/mnews/article/016/0002159332?sid=105\" class=\"nclicks(rig.secteco)\" title=\"“올 여름 비키니 입을래” 무리한 다이어트 ‘이 병’ 부른다\">“올 여름 비키니 입을래” 무리한 다이어트 ‘이 병’ 부른다</a>","link":"https://n.news.naver.com/mnews/article/016/0002159332?sid=105","retrieved":1687374632703},{"title":"'브누아 드 라당스' 최우수 여성무용수상에 강미선…다섯번째 한국인 수상","contents":"<a href=\"https://n.news.naver.com/mnews/article/421/0006878420?sid=103\" class=\"nclicks(rig.secteco)\" title=\"'브누아 드 라당스' 최우수 여성무용수상에 강미선…다섯번째 한국인 수상\">'브누아 드 라당스' 최우수 여성무용수상에 강미선…다섯번째 한국인 수상</a>","link":"https://n.news.naver.com/mnews/article/421/0006878420?sid=103","retrieved":1687374632707}]}