{"title":"네이버 뉴스 ─ 분야별 주요뉴스","url":"https://news.naver.com/main/main.naver?mode=LSD&mid=shm&sid1=100","favicon":"https://news.naver.com/main/favicon.ico","elements":[{"title":"‘한달에 450만원’…이재명 “요양병원부터 간병비 급여화 추진”","contents":"<a href=\"https://n.news.naver.com/mnews/article/009/0005221891?sid=100\" class=\"nclicks(rig.secteco)\" title=\"‘한달에 450만원’…이재명 “요양병원부터 간병비 급여화 추진”\">‘한달에 450만원’…이재명 “요양병원부터 간병비 급여화 추진”</a>","link":"https://n.news.naver.com/mnews/article/009/0005221891?sid=100","retrieved":1701169883092},{"title":"민주, 이동관 방통위원장·손준성·이정섭 검사 탄핵안 제출","contents":"<a href=\"https://n.news.naver.com/mnews/article/087/0001009879?sid=100\" class=\"nclicks(rig.secteco)\" title=\"민주, 이동관 방통위원장·손준성·이정섭 검사 탄핵안 제출\">민주, 이동관 방통위원장·손준성·이정섭 검사 탄핵안 제출</a>","link":"https://n.news.naver.com/mnews/article/087/0001009879?sid=100","retrieved":1701169883092},{"title":"이종석 헌재소장 후보자 청문보고서 채택… 30일 본회의 상정","contents":"<a href=\"https://n.news.naver.com/mnews/article/417/0000965164?sid=100\" class=\"nclicks(rig.secteco)\" title=\"이종석 헌재소장 후보자 청문보고서 채택… 30일 본회의 상정\">이종석 헌재소장 후보자 청문보고서 채택… 30일 본회의 상정</a>","link":"https://n.news.naver.com/mnews/article/417/0000965164?sid=100","retrieved":1701169883093},{"title":"‘COP 28’ 개최 UAE 속셈은 석유 거래?…12개국에 사업 제안한 문건","contents":"<a href=\"https://n.news.naver.com/mnews/article/081/0003412261?sid=104\" class=\"nclicks(rig.secteco)\" title=\"‘COP 28’ 개최 UAE 속셈은 석유 거래?…12개국에 사업 제안한 문건\">‘COP 28’ 개최 UAE 속셈은 석유 거래?…12개국에 사업 제안한 문건</a>","link":"https://n.news.naver.com/mnews/article/081/0003412261?sid=104","retrieved":1701169883093},{"title":"\"伊탈표 잡아라\"…韓, 오일머니 맞서 '후회없는 투혼'","contents":"<a href=\"https://n.news.naver.com/mnews/article/009/0005222011?sid=100\" class=\"nclicks(rig.secteco)\" title=\"&quot;伊탈표 잡아라&quot;…韓, 오일머니 맞서 '후회없는 투혼'\">\"伊탈표 잡아라\"…韓, 오일머니 맞서 '후회없는 투혼'</a>","link":"https://n.news.naver.com/mnews/article/009/0005222011?sid=100","retrieved":1701169883093},{"title":"인천·울산 등 자율주행 시범지구 신규 선정…전국 모든 시도 확대","contents":"<a href=\"https://n.news.naver.com/mnews/article/018/0005628088?sid=101\" class=\"nclicks(rig.secteco)\" title=\"인천·울산 등 자율주행 시범지구 신규 선정…전국 모든 시도 확대\">인천·울산 등 자율주행 시범지구 신규 선정…전국 모든 시도 확대</a>","link":"https://n.news.naver.com/mnews/article/018/0005628088?sid=101","retrieved":1701169883093},{"title":"고개 숙이는 달러에 뛰는 금값… “금리 빠지면 더 간다”","contents":"<a href=\"https://n.news.naver.com/mnews/article/005/0001655547?sid=101\" class=\"nclicks(rig.secteco)\" title=\"고개 숙이는 달러에 뛰는 금값… “금리 빠지면 더 간다”\">고개 숙이는 달러에 뛰는 금값… “금리 빠지면 더 간다”</a>","link":"https://n.news.naver.com/mnews/article/005/0001655547?sid=101","retrieved":1701169883094},{"title":"중기중앙회 \"기업승계 지원법안 연내 국회 통과해야\"","contents":"<a href=\"https://n.news.naver.com/mnews/article/001/0014357922?sid=101\" class=\"nclicks(rig.secteco)\" title=\"중기중앙회 &quot;기업승계 지원법안 연내 국회 통과해야&quot;\">중기중앙회 \"기업승계 지원법안 연내 국회 통과해야\"</a>","link":"https://n.news.naver.com/mnews/article/001/0014357922?sid=101","retrieved":1701169883096},{"title":"김연수 한컴 대표 \"AI사업 본격화…5년 내 글로벌 빅테크 목표\"","contents":"<a href=\"https://n.news.naver.com/mnews/article/003/0012235853?sid=105\" class=\"nclicks(rig.secteco)\" title=\"김연수 한컴 대표 &quot;AI사업 본격화…5년 내 글로벌 빅테크 목표&quot;\">김연수 한컴 대표 \"AI사업 본격화…5년 내 글로벌 빅테크 목표\"</a>","link":"https://n.news.naver.com/mnews/article/003/0012235853?sid=105","retrieved":1701169883098},{"title":"SK텔레콤 \"누구 비즈콜, 취약계층 4천63명 전문 상담 연결\"","contents":"<a href=\"https://n.news.naver.com/mnews/article/001/0014357829?sid=105\" class=\"nclicks(rig.secteco)\" title=\"SK텔레콤 &quot;누구 비즈콜, 취약계층 4천63명 전문 상담 연결&quot;\">SK텔레콤 \"누구 비즈콜, 취약계층 4천63명 전문 상담 연결\"</a>","link":"https://n.news.naver.com/mnews/article/001/0014357829?sid=105","retrieved":1701169883099},{"title":"\"청렴도시 선도\"…안양시, 자체감사 활동 '전국 1등'","contents":"<a href=\"https://n.news.naver.com/mnews/article/079/0003837966?sid=102\" class=\"nclicks(rig.secteco)\" title=\"&quot;청렴도시 선도&quot;…안양시, 자체감사 활동 '전국 1등'\">\"청렴도시 선도\"…안양시, 자체감사 활동 '전국 1등'</a>","link":"https://n.news.naver.com/mnews/article/079/0003837966?sid=102","retrieved":1701169883100},{"title":"경실련 “현역 의원 중 22명 자질 의심”…박덕흠 김철민 등 명단 공개","contents":"<a href=\"https://n.news.naver.com/mnews/article/005/0001655500?sid=102\" class=\"nclicks(rig.secteco)\" title=\"경실련 “현역 의원 중 22명 자질 의심”…박덕흠 김철민 등 명단 공개\">경실련 “현역 의원 중 22명 자질 의심”…박덕흠 김철민 등 명단 공개</a>","link":"https://n.news.naver.com/mnews/article/005/0001655500?sid=102","retrieved":1701169883102},{"title":"개최지 선정 투표 눈앞...부산시민 '한마음 한뜻'  응원전","contents":"<a href=\"https://n.news.naver.com/mnews/article/052/0001965669?sid=102\" class=\"nclicks(rig.secteco)\" title=\"개최지 선정 투표 눈앞...부산시민 '한마음 한뜻'  응원전\">개최지 선정 투표 눈앞...부산시민 '한마음 한뜻'  응원전</a>","link":"https://n.news.naver.com/mnews/article/052/0001965669?sid=102","retrieved":1701169883105},{"title":"츠지 토모쿠니 산리오 대표 “헬로키티 50주년…K팝 아이돌과 협업 늘릴 것”","contents":"<a href=\"https://n.news.naver.com/mnews/article/030/0003160871?sid=105\" class=\"nclicks(rig.secteco)\" title=\"츠지 토모쿠니 산리오 대표 “헬로키티 50주년…K팝 아이돌과 협업 늘릴 것”\">츠지 토모쿠니 산리오 대표 “헬로키티 50주년…K팝 아이돌과 협업 늘릴 것”</a>","link":"https://n.news.naver.com/mnews/article/030/0003160871?sid=105","retrieved":1701169883106},{"title":"대부분 지역서 영하권 날씨 지속…일부 지역은 눈·비 내려 [내일날씨]","contents":"<a href=\"https://n.news.naver.com/mnews/article/018/0005628374?sid=102\" class=\"nclicks(rig.secteco)\" title=\"대부분 지역서 영하권 날씨 지속…일부 지역은 눈·비 내려 [내일날씨]\">대부분 지역서 영하권 날씨 지속…일부 지역은 눈·비 내려 [내일날씨]</a>","link":"https://n.news.naver.com/mnews/article/018/0005628374?sid=102","retrieved":1701169883108}]}