{"title":"네이버 뉴스 ─ 분야별 주요뉴스","url":"https://news.naver.com/main/main.naver?mode=LSD&mid=shm&sid1=100","favicon":"https://news.naver.com/main/favicon.ico","elements":[{"title":"尹 “어떤 상황서도 안심 치료 받아야”… 어린이 전문진료센터 14곳으로 확대","contents":"<a href=\"https://n.news.naver.com/mnews/article/022/0003786104?sid=100\" class=\"nclicks(rig.secteco)\" title=\"尹 “어떤 상황서도 안심 치료 받아야”… 어린이 전문진료센터 14곳으로 확대\">尹 “어떤 상황서도 안심 치료 받아야”… 어린이 전문진료센터 14곳으로 확대</a>","link":"https://n.news.naver.com/mnews/article/022/0003786104?sid=100","retrieved":1677060966855},{"title":"'다케시마의 날'에 '일본해'에서 한미일 훈련?","contents":"<a href=\"https://n.news.naver.com/mnews/article/214/0001255632?sid=100\" class=\"nclicks(rig.secteco)\" title=\"'다케시마의 날'에 '일본해'에서 한미일 훈련?\">'다케시마의 날'에 '일본해'에서 한미일 훈련?</a>","link":"https://n.news.naver.com/mnews/article/214/0001255632?sid=100","retrieved":1677060966855},{"title":"日, ‘다케시마 날’ 맞아 “독도는 일본 땅” 또 억지 주장","contents":"<a href=\"https://n.news.naver.com/mnews/article/277/0005221893?sid=100\" class=\"nclicks(rig.secteco)\" title=\"日, ‘다케시마 날’ 맞아 “독도는 일본 땅” 또 억지 주장\">日, ‘다케시마 날’ 맞아 “독도는 일본 땅” 또 억지 주장</a>","link":"https://n.news.naver.com/mnews/article/277/0005221893?sid=100","retrieved":1677064358504},{"title":"“군비통제 시대 폐막 신호”… 미·중·러 핵 경쟁 촉발 부를 수도","contents":"<a href=\"https://n.news.naver.com/mnews/article/022/0003786103?sid=104\" class=\"nclicks(rig.secteco)\" title=\"“군비통제 시대 폐막 신호”… 미·중·러 핵 경쟁 촉발 부를 수도\">“군비통제 시대 폐막 신호”… 미·중·러 핵 경쟁 촉발 부를 수도</a>","link":"https://n.news.naver.com/mnews/article/022/0003786103?sid=104","retrieved":1677060966857},{"title":"동병상련의 中·러 급속 밀착… “양국관계는 굳건”","contents":"<a href=\"https://n.news.naver.com/mnews/article/022/0003786132?sid=104\" class=\"nclicks(rig.secteco)\" title=\"동병상련의 中·러 급속 밀착… “양국관계는 굳건”\">동병상련의 中·러 급속 밀착… “양국관계는 굳건”</a>","link":"https://n.news.naver.com/mnews/article/022/0003786132?sid=104","retrieved":1677064358508},{"title":"BTS·에스파가 한 집에…'무적함대' 하이브에 떨고 있는 가요계","contents":"<a href=\"https://n.news.naver.com/mnews/article/025/0003261405?sid=101\" class=\"nclicks(rig.secteco)\" title=\"BTS·에스파가 한 집에…'무적함대' 하이브에 떨고 있는 가요계\">BTS·에스파가 한 집에…'무적함대' 하이브에 떨고 있는 가요계</a>","link":"https://n.news.naver.com/mnews/article/025/0003261405?sid=101","retrieved":1677053935650},{"title":"악! 합계출산율 0.78명 ?대한민국 사라지나","contents":"<a href=\"https://n.news.naver.com/mnews/article/662/0000015007?sid=101\" class=\"nclicks(rig.secteco)\" title=\"악! 합계출산율 0.78명 ?대한민국 사라지나\">악! 합계출산율 0.78명 ?대한민국 사라지나</a>","link":"https://n.news.naver.com/mnews/article/662/0000015007?sid=101","retrieved":1677064358512},{"title":"이통3사 \"UAM 하늘길 연다\"...K-도심항공교통 본궤도(종합)","contents":"<a href=\"https://n.news.naver.com/mnews/article/031/0000730123?sid=101\" class=\"nclicks(rig.secteco)\" title=\"이통3사 &quot;UAM 하늘길 연다&quot;...K-도심항공교통 본궤도(종합)\">이통3사 \"UAM 하늘길 연다\"...K-도심항공교통 본궤도(종합)</a>","link":"https://n.news.naver.com/mnews/article/031/0000730123?sid=101","retrieved":1677064358513},{"title":"[단독]카카오, 한국어 잘하는 '코챗GPT' 내놓는다","contents":"<a href=\"https://n.news.naver.com/mnews/article/018/0005430073?sid=105\" class=\"nclicks(rig.secteco)\" title=\"[단독]카카오, 한국어 잘하는 '코챗GPT' 내놓는다\">[단독]카카오, 한국어 잘하는 '코챗GPT' 내놓는다</a>","link":"https://n.news.naver.com/mnews/article/018/0005430073?sid=105","retrieved":1677064358515},{"title":"[아!이뉴스] 택시 요금 오르니 이용자도↓…강신철 협회장 '5연임'","contents":"<a href=\"https://n.news.naver.com/mnews/article/031/0000730251?sid=105\" class=\"nclicks(rig.secteco)\" title=\"[아!이뉴스] 택시 요금 오르니 이용자도↓…강신철 협회장 '5연임'\">[아!이뉴스] 택시 요금 오르니 이용자도↓…강신철 협회장 '5연임'</a>","link":"https://n.news.naver.com/mnews/article/031/0000730251?sid=105","retrieved":1677064358517},{"title":"김성태 \"형님 잘 생각해보라\"…이화영은 2차 대질서도 \"모른다\"","contents":"<a href=\"https://n.news.naver.com/mnews/article/025/0003261452?sid=102\" class=\"nclicks(rig.secteco)\" title=\"김성태 &quot;형님 잘 생각해보라&quot;…이화영은 2차 대질서도 &quot;모른다&quot;\">김성태 \"형님 잘 생각해보라\"…이화영은 2차 대질서도 \"모른다\"</a>","link":"https://n.news.naver.com/mnews/article/025/0003261452?sid=102","retrieved":1677064358518},{"title":"재산분할 '기각', 혼인신고 '반려'…'동성 커플' 소송 20년 보니","contents":"<a href=\"https://n.news.naver.com/mnews/article/025/0003261443?sid=102\" class=\"nclicks(rig.secteco)\" title=\"재산분할 '기각', 혼인신고 '반려'…'동성 커플' 소송 20년 보니\">재산분할 '기각', 혼인신고 '반려'…'동성 커플' 소송 20년 보니</a>","link":"https://n.news.naver.com/mnews/article/025/0003261443?sid=102","retrieved":1677060966870},{"title":"3월부터 중국발 입국자 입국 후 PCR 검사 해제, 입국 전 음성증명서는 유지","contents":"<a href=\"https://n.news.naver.com/mnews/article/025/0003261455?sid=102\" class=\"nclicks(rig.secteco)\" title=\"3월부터 중국발 입국자 입국 후 PCR 검사 해제, 입국 전 음성증명서는 유지\">3월부터 중국발 입국자 입국 후 PCR 검사 해제, 입국 전 음성증명서는 유지</a>","link":"https://n.news.naver.com/mnews/article/025/0003261455?sid=102","retrieved":1677064358521},{"title":"韓 ‘2023 올해의 차’, 종합 80.75점으로 ‘현대차 그랜저’가 차지","contents":"<a href=\"https://n.news.naver.com/mnews/article/009/0005092463?sid=103\" class=\"nclicks(rig.secteco)\" title=\"韓 ‘2023 올해의 차’, 종합 80.75점으로 ‘현대차 그랜저’가 차지\">韓 ‘2023 올해의 차’, 종합 80.75점으로 ‘현대차 그랜저’가 차지</a>","link":"https://n.news.naver.com/mnews/article/009/0005092463?sid=103","retrieved":1677060966874},{"title":"\"현대차 디자인 세계최고 수준 의미… 열정적 인재들의 창의적 노력 덕분\"","contents":"<a href=\"https://n.news.naver.com/mnews/article/029/0002785769?sid=103\" class=\"nclicks(rig.secteco)\" title=\"&quot;현대차 디자인 세계최고 수준 의미… 열정적 인재들의 창의적 노력 덕분&quot;\">\"현대차 디자인 세계최고 수준 의미… 열정적 인재들의 창의적 노력 덕분\"</a>","link":"https://n.news.naver.com/mnews/article/029/0002785769?sid=103","retrieved":1677064358525}]}