{"title":"네이버 뉴스 ─ 분야별 주요뉴스","url":"https://news.naver.com/main/main.naver?mode=LSD&mid=shm&sid1=100","favicon":"https://news.naver.com/main/favicon.ico","elements":[{"title":"'정치편향' 논란 아랑곳 않던 김원웅, 횡령 의혹에 백기","contents":"<a href=\"https://news.naver.com/main/read.naver?mode=LSD&amp;mid=shm&amp;sid1=100&amp;oid=001&amp;aid=0012989778\" class=\"nclicks(rig.secteco)\" title=\"'정치편향' 논란 아랑곳 않던 김원웅, 횡령 의혹에 백기\">'정치편향' 논란 아랑곳 않던 김원웅, 횡령 의혹에 백기</a>","link":"https://news.naver.com/main/read.naver?mode=LSD&mid=shm&sid1=100&oid=001&aid=0012989778","retrieved":1644985084670},{"title":"'安유세차' 사고 여파에…애도 모드 속 '스피커' 끈 여야 후보들","contents":"<a href=\"https://news.naver.com/main/read.naver?mode=LSD&amp;mid=shm&amp;sid1=100&amp;oid=001&amp;aid=0012989805\" class=\"nclicks(rig.secteco)\" title=\"'安유세차' 사고 여파에…애도 모드 속 '스피커' 끈 여야 후보들\">'安유세차' 사고 여파에…애도 모드 속 '스피커' 끈 여야 후보들</a>","link":"https://news.naver.com/main/read.naver?mode=LSD&mid=shm&sid1=100&oid=001&aid=0012989805","retrieved":1644985084671},{"title":"광주 간 윤석열 “정치 보복 생각한 적 없고, 하지 않을 것”","contents":"<a href=\"https://news.naver.com/main/read.naver?mode=LSD&amp;mid=shm&amp;sid1=100&amp;oid=028&amp;aid=0002579399\" class=\"nclicks(rig.secteco)\" title=\"광주 간 윤석열 “정치 보복 생각한 적 없고, 하지 않을 것”\">광주 간 윤석열 “정치 보복 생각한 적 없고, 하지 않을 것”</a>","link":"https://news.naver.com/main/read.naver?mode=LSD&mid=shm&sid1=100&oid=028&aid=0002579399","retrieved":1644985084671},{"title":"러 일부 철군에 외교 돌파구 '기대감'…긴장감 해소는 '아직'(종합)","contents":"<a href=\"https://news.naver.com/main/read.naver?mode=LSD&amp;mid=shm&amp;sid1=104&amp;oid=421&amp;aid=0005909580\" class=\"nclicks(rig.secteco)\" title=\"러 일부 철군에 외교 돌파구 '기대감'…긴장감 해소는 '아직'(종합)\">러 일부 철군에 외교 돌파구 '기대감'…긴장감 해소는 '아직'(종합)</a>","link":"https://news.naver.com/main/read.naver?mode=LSD&mid=shm&sid1=104&oid=421&aid=0005909580","retrieved":1644985084673},{"title":"우크라 국방부·은행 사이트 마비…러시아 '사이버 공격'?","contents":"<a href=\"https://news.naver.com/main/read.naver?mode=LSD&amp;mid=shm&amp;sid1=104&amp;oid=008&amp;aid=0004708800\" class=\"nclicks(rig.secteco)\" title=\"우크라 국방부·은행 사이트 마비…러시아 '사이버 공격'?\">우크라 국방부·은행 사이트 마비…러시아 '사이버 공격'?</a>","link":"https://news.naver.com/main/read.naver?mode=LSD&mid=shm&sid1=104&oid=008&aid=0004708800","retrieved":1644985084673},{"title":"취업자 22년만에 최대? 3040은 ‘고용 붕괴’…文정부, ‘인구 감소 탓’ 변명","contents":"<a href=\"https://news.naver.com/main/read.naver?mode=LSD&amp;mid=shm&amp;sid1=101&amp;oid=366&amp;aid=0000794064\" class=\"nclicks(rig.secteco)\" title=\"취업자 22년만에 최대? 3040은 ‘고용 붕괴’…文정부, ‘인구 감소 탓’ 변명\">취업자 22년만에 최대? 3040은 ‘고용 붕괴’…文정부, ‘인구 감소 탓’ 변명</a>","link":"https://news.naver.com/main/read.naver?mode=LSD&mid=shm&sid1=101&oid=366&aid=0000794064","retrieved":1644981302707},{"title":"500만 삼성전자 개미 주주, 다음달 주총 사전투표하려면..","contents":"<a href=\"https://news.naver.com/main/read.naver?mode=LSD&amp;mid=shm&amp;sid1=101&amp;oid=023&amp;aid=0003673153\" class=\"nclicks(rig.secteco)\" title=\"500만 삼성전자 개미 주주, 다음달 주총 사전투표하려면..\">500만 삼성전자 개미 주주, 다음달 주총 사전투표하려면..</a>","link":"https://news.naver.com/main/read.naver?mode=LSD&mid=shm&sid1=101&oid=023&aid=0003673153","retrieved":1644985084673},{"title":"[단독]잠실5단지, 심의 통과…'오세훈표 재건축 정상화 1호' 탄생","contents":"<a href=\"https://news.naver.com/main/read.naver?mode=LSD&amp;mid=shm&amp;sid1=101&amp;oid=008&amp;aid=0004708810\" class=\"nclicks(rig.secteco)\" title=\"[단독]잠실5단지, 심의 통과…'오세훈표 재건축 정상화 1호' 탄생\">[단독]잠실5단지, 심의 통과…'오세훈표 재건축 정상화 1호' 탄생</a>","link":"https://news.naver.com/main/read.naver?mode=LSD&mid=shm&sid1=101&oid=008&aid=0004708810","retrieved":1644985084674},{"title":"네이버웹툰 글로벌 월간 이용자 8200만 명 돌파…인기작품 영상화 등 효과","contents":"<a href=\"https://news.naver.com/main/read.naver?mode=LSD&amp;mid=shm&amp;sid1=105&amp;oid=082&amp;aid=0001141623\" class=\"nclicks(rig.secteco)\" title=\"네이버웹툰 글로벌 월간 이용자 8200만 명 돌파…인기작품 영상화 등 효과\">네이버웹툰 글로벌 월간 이용자 8200만 명 돌파…인기작품 영상화 등 효과</a>","link":"https://news.naver.com/main/read.naver?mode=LSD&mid=shm&sid1=105&oid=082&aid=0001141623","retrieved":1644981302710},{"title":"네이버, 투자도 중소상공인 스케일업 지원기술에..스타트업 2곳 투자","contents":"<a href=\"https://news.naver.com/main/read.naver?mode=LSD&amp;mid=shm&amp;sid1=105&amp;oid=018&amp;aid=0005146693\" class=\"nclicks(rig.secteco)\" title=\"네이버, 투자도 중소상공인 스케일업 지원기술에..스타트업 2곳 투자\">네이버, 투자도 중소상공인 스케일업 지원기술에..스타트업 2곳 투자</a>","link":"https://news.naver.com/main/read.naver?mode=LSD&mid=shm&sid1=105&oid=018&aid=0005146693","retrieved":1644981302712},{"title":"등교전 신속항원검사 적극 권고…강제논란 피했으나 실효성 의문","contents":"<a href=\"https://news.naver.com/main/read.naver?mode=LSD&amp;mid=shm&amp;sid1=102&amp;oid=001&amp;aid=0012989783\" class=\"nclicks(rig.secteco)\" title=\"등교전 신속항원검사 적극 권고…강제논란 피했으나 실효성 의문\">등교전 신속항원검사 적극 권고…강제논란 피했으나 실효성 의문</a>","link":"https://news.naver.com/main/read.naver?mode=LSD&mid=shm&sid1=102&oid=001&aid=0012989783","retrieved":1644985084678},{"title":"유은혜, 경기지사 불출마…역대 최장수 교육부 장관 된다(종합2보)","contents":"<a href=\"https://news.naver.com/main/read.naver?mode=LSD&amp;mid=shm&amp;sid1=102&amp;oid=001&amp;aid=0012989873\" class=\"nclicks(rig.secteco)\" title=\"유은혜, 경기지사 불출마…역대 최장수 교육부 장관 된다(종합2보)\">유은혜, 경기지사 불출마…역대 최장수 교육부 장관 된다(종합2보)</a>","link":"https://news.naver.com/main/read.naver?mode=LSD&mid=shm&sid1=102&oid=001&aid=0012989873","retrieved":1644985084679},{"title":"\"김만배가 민주당 의원 측에 2억 원 전달\"…檢 진술 확보","contents":"<a href=\"https://news.naver.com/main/read.naver?mode=LSD&amp;mid=shm&amp;sid1=102&amp;oid=079&amp;aid=0003609959\" class=\"nclicks(rig.secteco)\" title=\"&quot;김만배가 민주당 의원 측에 2억 원 전달&quot;…檢 진술 확보\">\"김만배가 민주당 의원 측에 2억 원 전달\"…檢 진술 확보</a>","link":"https://news.naver.com/main/read.naver?mode=LSD&mid=shm&sid1=102&oid=079&aid=0003609959","retrieved":1644985084680},{"title":"정부, 한복 침략 좌시 않는다..올해의 문화유산 5가지 선정","contents":"<a href=\"https://news.naver.com/main/read.naver?mode=LSD&amp;mid=shm&amp;sid1=103&amp;oid=016&amp;aid=0001951558\" class=\"nclicks(rig.secteco)\" title=\"정부, 한복 침략 좌시 않는다..올해의 문화유산 5가지 선정\">정부, 한복 침략 좌시 않는다..올해의 문화유산 5가지 선정</a>","link":"https://news.naver.com/main/read.naver?mode=LSD&mid=shm&sid1=103&oid=016&aid=0001951558","retrieved":1644981302716},{"title":"코워킹 스페이스→공유업무공간 ‘쉬운 우리말’ 쓰세요","contents":"<a href=\"https://news.naver.com/main/read.naver?mode=LSD&amp;mid=shm&amp;sid1=103&amp;oid=018&amp;aid=0005147709\" class=\"nclicks(rig.secteco)\" title=\"코워킹 스페이스→공유업무공간 ‘쉬운 우리말’ 쓰세요\">코워킹 스페이스→공유업무공간 ‘쉬운 우리말’ 쓰세요</a>","link":"https://news.naver.com/main/read.naver?mode=LSD&mid=shm&sid1=103&oid=018&aid=0005147709","retrieved":1644981302717}]}