{"title":"네이버 뉴스 ─ 분야별 주요뉴스","url":"https://news.naver.com/main/main.naver?mode=LSD&mid=shm&sid1=100","favicon":"https://news.naver.com/main/favicon.ico","elements":[{"title":"강훈식 단일화없이 사퇴…민주 전대, 이재명-박용진 2파전 재편(종합)","contents":"<a href=\"https://n.news.naver.com/mnews/article/001/0013375758?sid=100\" class=\"nclicks(rig.secteco)\" title=\"강훈식 단일화없이 사퇴…민주 전대, 이재명-박용진 2파전 재편(종합)\">강훈식 단일화없이 사퇴…민주 전대, 이재명-박용진 2파전 재편(종합)</a>","link":"https://n.news.naver.com/mnews/article/001/0013375758?sid=100","retrieved":1660544489453},{"title":"[녹취구성] 윤대통령 \"독립운동은 자유 추구…일본은 힘 합칠 이웃\"","contents":"<a href=\"https://n.news.naver.com/mnews/article/422/0000555878?sid=100\" class=\"nclicks(rig.secteco)\" title=\"[녹취구성] 윤대통령 &quot;독립운동은 자유 추구…일본은 힘 합칠 이웃&quot;\">[녹취구성] 윤대통령 \"독립운동은 자유 추구…일본은 힘 합칠 이웃\"</a>","link":"https://n.news.naver.com/mnews/article/422/0000555878?sid=100","retrieved":1660544489456},{"title":"尹 \"北, 실질적 비핵화 전환한다면 대규모 식량·인프라 지원\"(종합)","contents":"<a href=\"https://n.news.naver.com/mnews/article/001/0013375451?sid=100\" class=\"nclicks(rig.secteco)\" title=\"尹 &quot;北, 실질적 비핵화 전환한다면 대규모 식량·인프라 지원&quot;(종합)\">尹 \"北, 실질적 비핵화 전환한다면 대규모 식량·인프라 지원\"(종합)</a>","link":"https://n.news.naver.com/mnews/article/001/0013375451?sid=100","retrieved":1660544489458},{"title":"尹 '한일관계 회복' 외친 날 日 야스쿠니 참배…정부 \"깊은 실망\"","contents":"<a href=\"https://n.news.naver.com/mnews/article/079/0003674798?sid=104\" class=\"nclicks(rig.secteco)\" title=\"尹 '한일관계 회복' 외친 날 日 야스쿠니 참배…정부 &quot;깊은 실망&quot;\">尹 '한일관계 회복' 외친 날 日 야스쿠니 참배…정부 \"깊은 실망\"</a>","link":"https://n.news.naver.com/mnews/article/079/0003674798?sid=104","retrieved":1660544489459},{"title":"“美의원단 대만 방문하면 강력대응”한다던 中… 그래서 나온 대응은?","contents":"<a href=\"https://n.news.naver.com/mnews/article/366/0000834215?sid=104\" class=\"nclicks(rig.secteco)\" title=\"“美의원단 대만 방문하면 강력대응”한다던 中… 그래서 나온 대응은?\">“美의원단 대만 방문하면 강력대응”한다던 中… 그래서 나온 대응은?</a>","link":"https://n.news.naver.com/mnews/article/366/0000834215?sid=104","retrieved":1660544489467},{"title":"경제계 “尹대통령 규제 개혁 의지, 매우 환영”","contents":"<a href=\"https://n.news.naver.com/mnews/article/366/0000834203?sid=101\" class=\"nclicks(rig.secteco)\" title=\"경제계 “尹대통령 규제 개혁 의지, 매우 환영”\">경제계 “尹대통령 규제 개혁 의지, 매우 환영”</a>","link":"https://n.news.naver.com/mnews/article/366/0000834203?sid=101","retrieved":1660539748964},{"title":"7월 車 수출액 첫 50억 달러 돌파…친환경차 수출 5만 대 넘어","contents":"<a href=\"https://n.news.naver.com/mnews/article/374/0000298836?sid=101\" class=\"nclicks(rig.secteco)\" title=\"7월 車 수출액 첫 50억 달러 돌파…친환경차 수출 5만 대 넘어\">7월 車 수출액 첫 50억 달러 돌파…친환경차 수출 5만 대 넘어</a>","link":"https://n.news.naver.com/mnews/article/374/0000298836?sid=101","retrieved":1660544489472},{"title":"다중채무자 446만명 추산…\"이대로 두면 금융위기\"","contents":"<a href=\"https://n.news.naver.com/mnews/article/018/0005292553?sid=101\" class=\"nclicks(rig.secteco)\" title=\"다중채무자 446만명 추산…&quot;이대로 두면 금융위기&quot;\">다중채무자 446만명 추산…\"이대로 두면 금융위기\"</a>","link":"https://n.news.naver.com/mnews/article/018/0005292553?sid=101","retrieved":1660544489473},{"title":"갤럭시 Z 플립4·갤럭시 Z 폴드4, 내일부터 사전 판매","contents":"<a href=\"https://n.news.naver.com/mnews/article/079/0003674799?sid=105\" class=\"nclicks(rig.secteco)\" title=\"갤럭시 Z 플립4·갤럭시 Z 폴드4, 내일부터 사전 판매\">갤럭시 Z 플립4·갤럭시 Z 폴드4, 내일부터 사전 판매</a>","link":"https://n.news.naver.com/mnews/article/079/0003674799?sid=105","retrieved":1660544489473},{"title":"“제 코골이 들어볼래요?” 양태종이 자랑한 ‘갤워치’ 최고 기능","contents":"<a href=\"https://n.news.naver.com/mnews/article/025/0003216684?sid=105\" class=\"nclicks(rig.secteco)\" title=\"“제 코골이 들어볼래요?” 양태종이 자랑한 ‘갤워치’ 최고 기능\">“제 코골이 들어볼래요?” 양태종이 자랑한 ‘갤워치’ 최고 기능</a>","link":"https://n.news.naver.com/mnews/article/025/0003216684?sid=105","retrieved":1660535738138},{"title":"서울시, 20만 반지하주택 '공공임대 재건축 아파트'로 옮긴다","contents":"<a href=\"https://n.news.naver.com/mnews/article/008/0004782996?sid=102\" class=\"nclicks(rig.secteco)\" title=\"서울시, 20만 반지하주택 '공공임대 재건축 아파트'로 옮긴다\">서울시, 20만 반지하주택 '공공임대 재건축 아파트'로 옮긴다</a>","link":"https://n.news.naver.com/mnews/article/008/0004782996?sid=102","retrieved":1660544489475},{"title":"尹 광복절 “한일관계 개선”…이용수할머니 “사죄 먼저”(종합)","contents":"<a href=\"https://n.news.naver.com/mnews/article/081/0003294534?sid=102\" class=\"nclicks(rig.secteco)\" title=\"尹 광복절 “한일관계 개선”…이용수할머니 “사죄 먼저”(종합)\">尹 광복절 “한일관계 개선”…이용수할머니 “사죄 먼저”(종합)</a>","link":"https://n.news.naver.com/mnews/article/081/0003294534?sid=102","retrieved":1660544489475},{"title":"코로나19 신규 확진 6만2078명…위중증 108일만 '최다'","contents":"<a href=\"https://n.news.naver.com/mnews/article/031/0000691789?sid=102\" class=\"nclicks(rig.secteco)\" title=\"코로나19 신규 확진 6만2078명…위중증 108일만 '최다'\">코로나19 신규 확진 6만2078명…위중증 108일만 '최다'</a>","link":"https://n.news.naver.com/mnews/article/031/0000691789?sid=102","retrieved":1660544489475},{"title":"오늘 '1시간 50㎜ 이상' 폭우 가능성…늦은오후 중부지방부터 비(종합)","contents":"<a href=\"https://n.news.naver.com/mnews/article/001/0013375489?sid=103\" class=\"nclicks(rig.secteco)\" title=\"오늘 '1시간 50㎜ 이상' 폭우 가능성…늦은오후 중부지방부터 비(종합)\">오늘 '1시간 50㎜ 이상' 폭우 가능성…늦은오후 중부지방부터 비(종합)</a>","link":"https://n.news.naver.com/mnews/article/001/0013375489?sid=103","retrieved":1660544489478},{"title":"90대도 응원봉 환호…티빙 10명중 9명이 임영웅에 몰렸다","contents":"<a href=\"https://n.news.naver.com/mnews/article/025/0003216702?sid=103\" class=\"nclicks(rig.secteco)\" title=\"90대도 응원봉 환호…티빙 10명중 9명이 임영웅에 몰렸다\">90대도 응원봉 환호…티빙 10명중 9명이 임영웅에 몰렸다</a>","link":"https://n.news.naver.com/mnews/article/025/0003216702?sid=103","retrieved":1660544489479}]}