{"title":"네이버 뉴스 ─ 분야별 주요뉴스","url":"https://news.naver.com/main/main.naver?mode=LSD&mid=shm&sid1=100","favicon":"https://news.naver.com/main/favicon.ico","elements":[{"title":"안전운임제, 與 \"원점검토\"에도…野 국토위서 '3년 연장' 강행(종합)","contents":"<a href=\"https://n.news.naver.com/mnews/article/018/0005384055?sid=100\" class=\"nclicks(rig.secteco)\" title=\"안전운임제, 與 &quot;원점검토&quot;에도…野 국토위서 '3년 연장' 강행(종합)\">안전운임제, 與 \"원점검토\"에도…野 국토위서 '3년 연장' 강행(종합)</a>","link":"https://n.news.naver.com/mnews/article/018/0005384055?sid=100","retrieved":1670562813160},{"title":"여야, 정기국회 마지막날까지 끝장대치…예산안 담판 '안갯속'","contents":"<a href=\"https://n.news.naver.com/mnews/article/001/0013633283?sid=100\" class=\"nclicks(rig.secteco)\" title=\"여야, 정기국회 마지막날까지 끝장대치…예산안 담판 '안갯속'\">여야, 정기국회 마지막날까지 끝장대치…예산안 담판 '안갯속'</a>","link":"https://n.news.naver.com/mnews/article/001/0013633283?sid=100","retrieved":1670559429193},{"title":"윤 대통령, 긍정 33%... 중도5%p↑, 노조 대응 덕분?","contents":"<a href=\"https://n.news.naver.com/mnews/article/047/0002375550?sid=100\" class=\"nclicks(rig.secteco)\" title=\"윤 대통령, 긍정 33%... 중도5%p↑, 노조 대응 덕분?\">윤 대통령, 긍정 33%... 중도5%p↑, 노조 대응 덕분?</a>","link":"https://n.news.naver.com/mnews/article/047/0002375550?sid=100","retrieved":1670562813163},{"title":"[커버스토리]中-사우디 '포괄적 전략동반자' 관계 격상…美와 결별 빨라지나","contents":"<a href=\"https://n.news.naver.com/mnews/article/277/0005189734?sid=104\" class=\"nclicks(rig.secteco)\" title=\"[커버스토리]中-사우디 '포괄적 전략동반자' 관계 격상…美와 결별 빨라지나\">[커버스토리]中-사우디 '포괄적 전략동반자' 관계 격상…美와 결별 빨라지나</a>","link":"https://n.news.naver.com/mnews/article/277/0005189734?sid=104","retrieved":1670555834390},{"title":"美농구스타 그라이너와 맞교환한 러 무기상 모스크바 도착","contents":"<a href=\"https://n.news.naver.com/mnews/article/001/0013632943?sid=104\" class=\"nclicks(rig.secteco)\" title=\"美농구스타 그라이너와 맞교환한 러 무기상 모스크바 도착\">美농구스타 그라이너와 맞교환한 러 무기상 모스크바 도착</a>","link":"https://n.news.naver.com/mnews/article/001/0013632943?sid=104","retrieved":1670562813166},{"title":"한전법 개정안 부결 ‘후폭풍’…정부·국회 “조속한 시일 내 재추진”","contents":"<a href=\"https://n.news.naver.com/mnews/article/018/0005384063?sid=101\" class=\"nclicks(rig.secteco)\" title=\"한전법 개정안 부결 ‘후폭풍’…정부·국회 “조속한 시일 내 재추진”\">한전법 개정안 부결 ‘후폭풍’…정부·국회 “조속한 시일 내 재추진”</a>","link":"https://n.news.naver.com/mnews/article/018/0005384063?sid=101","retrieved":1670562813167},{"title":"10월 경상수지 8.8억달러, 가까스로 흑자…\"올 연말부턴 아슬아슬\"(종합)","contents":"<a href=\"https://n.news.naver.com/mnews/article/018/0005383902?sid=101\" class=\"nclicks(rig.secteco)\" title=\"10월 경상수지 8.8억달러, 가까스로 흑자…&quot;올 연말부턴 아슬아슬&quot;(종합)\">10월 경상수지 8.8억달러, 가까스로 흑자…\"올 연말부턴 아슬아슬\"(종합)</a>","link":"https://n.news.naver.com/mnews/article/018/0005383902?sid=101","retrieved":1670553830615},{"title":"해외에서도 퇴출 위기 위믹스…갈 곳이 없다","contents":"<a href=\"https://n.news.naver.com/mnews/article/277/0005189771?sid=101\" class=\"nclicks(rig.secteco)\" title=\"해외에서도 퇴출 위기 위믹스…갈 곳이 없다\">해외에서도 퇴출 위기 위믹스…갈 곳이 없다</a>","link":"https://n.news.naver.com/mnews/article/277/0005189771?sid=101","retrieved":1670562813170},{"title":"네이버, 스포츠·패션 주제에 스마트블록 비중 확대","contents":"<a href=\"https://n.news.naver.com/mnews/article/003/0011581608?sid=105\" class=\"nclicks(rig.secteco)\" title=\"네이버, 스포츠·패션 주제에 스마트블록 비중 확대\">네이버, 스포츠·패션 주제에 스마트블록 비중 확대</a>","link":"https://n.news.naver.com/mnews/article/003/0011581608?sid=105","retrieved":1670562813171},{"title":"일본이 우주기술 독자 개발했더니... 미국 태도가 변했다","contents":"<a href=\"https://n.news.naver.com/mnews/article/469/0000712000?sid=105\" class=\"nclicks(rig.secteco)\" title=\"일본이 우주기술 독자 개발했더니... 미국 태도가 변했다\">일본이 우주기술 독자 개발했더니... 미국 태도가 변했다</a>","link":"https://n.news.naver.com/mnews/article/469/0000712000?sid=105","retrieved":1670555834400},{"title":"[속보] 화물연대 “파업 철회·업무 복귀”…조합원 투표 결과 공개","contents":"<a href=\"https://n.news.naver.com/mnews/article/056/0011389785?sid=102\" class=\"nclicks(rig.secteco)\" title=\"[속보] 화물연대 “파업 철회·업무 복귀”…조합원 투표 결과 공개\">[속보] 화물연대 “파업 철회·업무 복귀”…조합원 투표 결과 공개</a>","link":"https://n.news.naver.com/mnews/article/056/0011389785?sid=102","retrieved":1670562813174},{"title":"중대본 \"실내 마스크 착용 의무 폐지… 권고·자율 착용으로\"","contents":"<a href=\"https://n.news.naver.com/mnews/article/346/0000056355?sid=102\" class=\"nclicks(rig.secteco)\" title=\"중대본 &quot;실내 마스크 착용 의무 폐지… 권고·자율 착용으로&quot;\">중대본 \"실내 마스크 착용 의무 폐지… 권고·자율 착용으로\"</a>","link":"https://n.news.naver.com/mnews/article/346/0000056355?sid=102","retrieved":1670562813175},{"title":"[속보] ‘2억4000만 원 뇌물수수’ 정진상 구속 기소","contents":"<a href=\"https://n.news.naver.com/mnews/article/056/0011389784?sid=102\" class=\"nclicks(rig.secteco)\" title=\"[속보] ‘2억4000만 원 뇌물수수’ 정진상 구속 기소\">[속보] ‘2억4000만 원 뇌물수수’ 정진상 구속 기소</a>","link":"https://n.news.naver.com/mnews/article/056/0011389784?sid=102","retrieved":1670562813176},{"title":"\"각 그랜저에 아빠들 신날 만하네\"…디 올 뉴 그랜저[타봤어요]","contents":"<a href=\"https://n.news.naver.com/mnews/article/018/0005384032?sid=103\" class=\"nclicks(rig.secteco)\" title=\"&quot;각 그랜저에 아빠들 신날 만하네&quot;…디 올 뉴 그랜저[타봤어요]\">\"각 그랜저에 아빠들 신날 만하네\"…디 올 뉴 그랜저[타봤어요]</a>","link":"https://n.news.naver.com/mnews/article/018/0005384032?sid=103","retrieved":1670555834407},{"title":"“빈 공장서 전기차 만들자”…‘악전고투’ 르·쌍·쉐, 전동화 전략은? [비즈360]","contents":"<a href=\"https://n.news.naver.com/mnews/article/016/0002076159?sid=103\" class=\"nclicks(rig.secteco)\" title=\"“빈 공장서 전기차 만들자”…‘악전고투’ 르·쌍·쉐, 전동화 전략은? [비즈360]\">“빈 공장서 전기차 만들자”…‘악전고투’ 르·쌍·쉐, 전동화 전략은? [비즈360]</a>","link":"https://n.news.naver.com/mnews/article/016/0002076159?sid=103","retrieved":1670559429206}]}